<odoo>
    <data noupdate="1">

        <record id="survey_root_quantitative_aptitude_indonesia_master" model="survey.survey">
            <field name="title">Quantitative Aptitude Test (Indonesia)</field>
            <field name="survey_type">general</field>
            <field name="questions_layout">one_page</field>
            <field name="is_time_limited" eval="True"/>
            <field name="time_limit">60</field>
            <field name="scoring_type">scoring_without_answers</field>
            <field name="scoring_success_min">80.0</field>
            <field name="state">open</field>
        </record>

        <record id="survey_question_quantitative_aptitude_indonesia_master_section_1" model="survey.question">
            <field name="title">Temukan suku yang hilang pada setiap deret berikut untuk pertanyaan nomor 1-3.</field>
            <field name="survey_id" ref="survey_root_quantitative_aptitude_indonesia_master" />
            <field name="is_page" eval="True"/>
            <field name="question_type" eval="False" />
        </record>

        <record id="survey_question_quantitative_aptitude_indonesia_master_1" model="survey.question">
            <field name="title">1. 2, 9, 28, 65, 126, …</field>
            <field name="question_type">simple_choice</field>
            <field name="survey_id" ref="survey_root_quantitative_aptitude_indonesia_master"/>
        </record>
        <record id="survey_question_quantitative_aptitude_indonesia_master_1_col_1" model="survey.question.answer">
            <field name="value">A. 195</field>
            <field name="is_correct" eval="False"/>
            <field name="answer_score">0.0</field>
            <field name="question_id" ref="survey_question_quantitative_aptitude_indonesia_master_1"/>
        </record>
        <record id="survey_question_quantitative_aptitude_indonesia_master_1_col_2" model="survey.question.answer">
            <field name="value">B. 199</field>
            <field name="is_correct" eval="False"/>
            <field name="answer_score">0.0</field>
            <field name="question_id" ref="survey_question_quantitative_aptitude_indonesia_master_1"/>
        </record>
        <record id="survey_question_quantitative_aptitude_indonesia_master_1_col_3" model="survey.question.answer">
            <field name="value">C. 208</field>
            <field name="is_correct" eval="False"/>
            <field name="answer_score">0.0</field>
            <field name="question_id" ref="survey_question_quantitative_aptitude_indonesia_master_1"/>
        </record>
        <record id="survey_question_quantitative_aptitude_indonesia_master_1_col_4" model="survey.question.answer">
            <field name="value">D. 217</field>
            <field name="is_correct" eval="True"/>
            <field name="answer_score">3.33</field>
            <field name="question_id" ref="survey_question_quantitative_aptitude_indonesia_master_1"/>
        </record>

        <record id="survey_question_quantitative_aptitude_indonesia_master_2" model="survey.question">
            <field name="title">2. 4, 18, … , 100, 180, 294</field>
            <field name="question_type">simple_choice</field>
            <field name="survey_id" ref="survey_root_quantitative_aptitude_indonesia_master"/>
        </record>
        <record id="survey_question_quantitative_aptitude_indonesia_master_2_col_1" model="survey.question.answer">
            <field name="value">A. 32</field>
            <field name="is_correct" eval="False"/>
            <field name="answer_score">0.0</field>
            <field name="question_id" ref="survey_question_quantitative_aptitude_indonesia_master_2"/>
        </record>
        <record id="survey_question_quantitative_aptitude_indonesia_master_2_col_2" model="survey.question.answer">
            <field name="value">B. 36</field>
            <field name="is_correct" eval="False"/>
            <field name="answer_score">0.0</field>
            <field name="question_id" ref="survey_question_quantitative_aptitude_indonesia_master_2"/>
        </record>
        <record id="survey_question_quantitative_aptitude_indonesia_master_2_col_3" model="survey.question.answer">
            <field name="value">C. 48</field>
            <field name="is_correct" eval="True"/>
            <field name="answer_score">3.33</field>
            <field name="question_id" ref="survey_question_quantitative_aptitude_indonesia_master_2"/>
        </record>
        <record id="survey_question_quantitative_aptitude_indonesia_master_2_col_4" model="survey.question.answer">
            <field name="value">D. 40</field>
            <field name="is_correct" eval="False"/>
            <field name="answer_score">0.0</field>
            <field name="question_id" ref="survey_question_quantitative_aptitude_indonesia_master_2"/>
        </record>

        <record id="survey_question_quantitative_aptitude_indonesia_master_3" model="survey.question">
            <field name="title">3. 600, 125, 30, … , 7.2, 6.44, 6.288</field>
            <field name="question_type">simple_choice</field>
            <field name="survey_id" ref="survey_root_quantitative_aptitude_indonesia_master"/>
        </record>
        <record id="survey_question_quantitative_aptitude_indonesia_master_3_col_1" model="survey.question.answer">
            <field name="value">A. 6</field>
            <field name="is_correct" eval="False"/>
            <field name="answer_score">0.0</field>
            <field name="question_id" ref="survey_question_quantitative_aptitude_indonesia_master_3"/>
        </record>
        <record id="survey_question_quantitative_aptitude_indonesia_master_3_col_2" model="survey.question.answer">
            <field name="value">B. 10</field>
            <field name="is_correct" eval="False"/>
            <field name="answer_score">0.0</field>
            <field name="question_id" ref="survey_question_quantitative_aptitude_indonesia_master_3"/>
        </record>
        <record id="survey_question_quantitative_aptitude_indonesia_master_3_col_3" model="survey.question.answer">
            <field name="value">C. 15</field>
            <field name="is_correct" eval="False"/>
            <field name="answer_score">0.0</field>
            <field name="question_id" ref="survey_question_quantitative_aptitude_indonesia_master_3"/>
        </record>
        <record id="survey_question_quantitative_aptitude_indonesia_master_3_col_4" model="survey.question.answer">
            <field name="value">D. 11</field>
            <field name="is_correct" eval="True"/>
            <field name="answer_score">3.33</field>
            <field name="question_id" ref="survey_question_quantitative_aptitude_indonesia_master_3"/>
        </record>

        <record id="survey_question_quantitative_aptitude_indonesia_master_4" model="survey.question">
            <field name="title">4. Berapa banyak bilangan antara 400 dan 500 yang habis dibagi 12, 15, dan 20?</field>
            <field name="question_type">simple_choice</field>
            <field name="survey_id" ref="survey_root_quantitative_aptitude_indonesia_master"/>
        </record>
        <record id="survey_question_quantitative_aptitude_indonesia_master_4_col_1" model="survey.question.answer">
            <field name="value">A. Satu</field>
            <field name="is_correct" eval="False"/>
            <field name="answer_score">0.0</field>
            <field name="question_id" ref="survey_question_quantitative_aptitude_indonesia_master_4"/>
        </record>
        <record id="survey_question_quantitative_aptitude_indonesia_master_4_col_2" model="survey.question.answer">
            <field name="value">B. Dua</field>
            <field name="is_correct" eval="True"/>
            <field name="answer_score">3.33</field>
            <field name="question_id" ref="survey_question_quantitative_aptitude_indonesia_master_4"/>
        </record>
        <record id="survey_question_quantitative_aptitude_indonesia_master_4_col_3" model="survey.question.answer">
            <field name="value">C. Tiga</field>
            <field name="is_correct" eval="False"/>
            <field name="answer_score">0.0</field>
            <field name="question_id" ref="survey_question_quantitative_aptitude_indonesia_master_4"/>
        </record>
        <record id="survey_question_quantitative_aptitude_indonesia_master_4_col_4" model="survey.question.answer">
            <field name="value">D. Tidak satupun di atas</field>
            <field name="is_correct" eval="False"/>
            <field name="answer_score">0.0</field>
            <field name="question_id" ref="survey_question_quantitative_aptitude_indonesia_master_4"/>
        </record>

        <record id="survey_question_quantitative_aptitude_indonesia_master_5" model="survey.question">
            <field name="title">5. Jumlah dua bilangan adalah 528 dan KPK-nya adalah 33. Banyaknya pasangan bilangan yang memenuhi syarat di atas adalah?</field>
            <field name="question_type">simple_choice</field>
            <field name="survey_id" ref="survey_root_quantitative_aptitude_indonesia_master"/>
        </record>
        <record id="survey_question_quantitative_aptitude_indonesia_master_5_col_1" model="survey.question.answer">
            <field name="value">A. 6</field>
            <field name="is_correct" eval="False"/>
            <field name="answer_score">0.0</field>
            <field name="question_id" ref="survey_question_quantitative_aptitude_indonesia_master_5"/>
        </record>
        <record id="survey_question_quantitative_aptitude_indonesia_master_5_col_2" model="survey.question.answer">
            <field name="value">B. 12</field>
            <field name="is_correct" eval="False"/>
            <field name="answer_score">0.0</field>
            <field name="question_id" ref="survey_question_quantitative_aptitude_indonesia_master_5"/>
        </record>
        <record id="survey_question_quantitative_aptitude_indonesia_master_5_col_3" model="survey.question.answer">
            <field name="value">C. 8</field>
            <field name="is_correct" eval="False"/>
            <field name="answer_score">0.0</field>
            <field name="question_id" ref="survey_question_quantitative_aptitude_indonesia_master_5"/>
        </record>
        <record id="survey_question_quantitative_aptitude_indonesia_master_5_col_4" model="survey.question.answer">
            <field name="value">D. 4</field>
            <field name="is_correct" eval="True"/>
            <field name="answer_score">3.33</field>
            <field name="question_id" ref="survey_question_quantitative_aptitude_indonesia_master_5"/>
        </record>

        <record id="survey_question_quantitative_aptitude_indonesia_master_6" model="survey.question">
            <field name="title">6. Usia rata-rata sebuah kelas adalah 15,8 tahun. Usia rata-rata anak laki-laki di kelas adalah 16,4 tahun sedangkan anak perempuan adalah 15,4 tahun. Berapa perbandingan anak laki-laki dan perempuan di kelas tersebut?</field>
            <field name="question_type">simple_choice</field>
            <field name="survey_id" ref="survey_root_quantitative_aptitude_indonesia_master"/>
        </record>
        <record id="survey_question_quantitative_aptitude_indonesia_master_6_col_1" model="survey.question.answer">
            <field name="value">A. 1:2</field>
            <field name="is_correct" eval="False"/>
            <field name="answer_score">0.0</field>
            <field name="question_id" ref="survey_question_quantitative_aptitude_indonesia_master_6"/>
        </record>
        <record id="survey_question_quantitative_aptitude_indonesia_master_6_col_2" model="survey.question.answer">
            <field name="value">B. 3:4</field>
            <field name="is_correct" eval="False"/>
            <field name="answer_score">0.0</field>
            <field name="question_id" ref="survey_question_quantitative_aptitude_indonesia_master_6"/>
        </record>
        <record id="survey_question_quantitative_aptitude_indonesia_master_6_col_3" model="survey.question.answer">
            <field name="value">C. 3:5</field>
            <field name="is_correct" eval="False"/>
            <field name="answer_score">0.0</field>
            <field name="question_id" ref="survey_question_quantitative_aptitude_indonesia_master_6"/>
        </record>
        <record id="survey_question_quantitative_aptitude_indonesia_master_6_col_4" model="survey.question.answer">
            <field name="value">D.Tidak satupun di atas</field>
            <field name="is_correct" eval="True"/>
            <field name="answer_score">3.33</field>
            <field name="question_id" ref="survey_question_quantitative_aptitude_indonesia_master_6"/>
        </record>

        <record id="survey_question_quantitative_aptitude_indonesia_master_7" model="survey.question">
            <field name="title">7. Tahun lalu, tim kriket India memainkan 40 pertandingan kriket satu hari di mana mereka hanya berhasil memenangkan 40%. Tahun ini, sejauh ini telah memainkan beberapa pertandingan, yang mengharuskannya untuk memenangkan 80% dari sisa pertandingan untuk mempertahankan persentase kemenangan yang ada. Temukan jumlah pertandingan yang dimainkan oleh India sepanjang tahun ini.</field>
            <field name="question_type">simple_choice</field>
            <field name="survey_id" ref="survey_root_quantitative_aptitude_indonesia_master"/>
        </record>
        <record id="survey_question_quantitative_aptitude_indonesia_master_7_col_1" model="survey.question.answer">
            <field name="value">A. 30</field>
            <field name="is_correct" eval="False"/>
            <field name="answer_score">0.0</field>
            <field name="question_id" ref="survey_question_quantitative_aptitude_indonesia_master_7"/>
        </record>
        <record id="survey_question_quantitative_aptitude_indonesia_master_7_col_2" model="survey.question.answer">
            <field name="value">B. 25</field>
            <field name="is_correct" eval="False"/>
            <field name="answer_score">0.0</field>
            <field name="question_id" ref="survey_question_quantitative_aptitude_indonesia_master_7"/>
        </record>
        <record id="survey_question_quantitative_aptitude_indonesia_master_7_col_3" model="survey.question.answer">
            <field name="value">C. 28</field>
            <field name="is_correct" eval="False"/>
            <field name="answer_score">0.0</field>
            <field name="question_id" ref="survey_question_quantitative_aptitude_indonesia_master_7"/>
        </record>
        <record id="survey_question_quantitative_aptitude_indonesia_master_7_col_4" model="survey.question.answer">
            <field name="value">D. Informasi Tidak Memadai</field>
            <field name="is_correct" eval="True"/>
            <field name="answer_score">3.33</field>
            <field name="question_id" ref="survey_question_quantitative_aptitude_indonesia_master_7"/>
        </record>

        <record id="survey_question_quantitative_aptitude_indonesia_master_8" model="survey.question">
            <field name="title">8. Harga beras turun 20%. Berapa banyak beras yang dapat dibeli sekarang dengan uang yang cukup untuk membeli 20 kg beras sebelumnya?</field>
            <field name="question_type">simple_choice</field>
            <field name="survey_id" ref="survey_root_quantitative_aptitude_indonesia_master"/>
        </record>
        <record id="survey_question_quantitative_aptitude_indonesia_master_8_col_1" model="survey.question.answer">
            <field name="value">A. 5 kg</field>
            <field name="is_correct" eval="False"/>
            <field name="answer_score">0.0</field>
            <field name="question_id" ref="survey_question_quantitative_aptitude_indonesia_master_8"/>
        </record>
        <record id="survey_question_quantitative_aptitude_indonesia_master_8_col_2" model="survey.question.answer">
            <field name="value">B. 15 kg</field>
            <field name="is_correct" eval="False"/>
            <field name="answer_score">0.0</field>
            <field name="question_id" ref="survey_question_quantitative_aptitude_indonesia_master_8"/>
        </record>
        <record id="survey_question_quantitative_aptitude_indonesia_master_8_col_3" model="survey.question.answer">
            <field name="value">C. 25 kg</field>
            <field name="is_correct" eval="True"/>
            <field name="answer_score">3.33</field>
            <field name="question_id" ref="survey_question_quantitative_aptitude_indonesia_master_8"/>
        </record>
        <record id="survey_question_quantitative_aptitude_indonesia_master_8_col_4" model="survey.question.answer">
            <field name="value">D. 30 kg</field>
            <field name="is_correct" eval="False"/>
            <field name="answer_score">0.0</field>
            <field name="question_id" ref="survey_question_quantitative_aptitude_indonesia_master_8"/>
        </record>

        <record id="survey_question_quantitative_aptitude_indonesia_master_9" model="survey.question">
            <field name="title">9.Seorang pedagang kain mengaku menjual bahannya dengan harga pokok tetapi menggunakan timbangan yang bertuliskan 1 m untuk 95 cm. Temukan persentase keuntungannya.</field>
            <field name="question_type">simple_choice</field>
            <field name="survey_id" ref="survey_root_quantitative_aptitude_indonesia_master"/>
        </record>
        <record id="survey_question_quantitative_aptitude_indonesia_master_9_col_1" model="survey.question.answer">
            <field name="value">A. 5.26%</field>
            <field name="is_correct" eval="True"/>
            <field name="answer_score">3.33</field>
            <field name="question_id" ref="survey_question_quantitative_aptitude_indonesia_master_9"/>
        </record>
        <record id="survey_question_quantitative_aptitude_indonesia_master_9_col_2" model="survey.question.answer">
            <field name="value">B. 6.2%</field>
            <field name="is_correct" eval="False"/>
            <field name="answer_score">0.0</field>
            <field name="question_id" ref="survey_question_quantitative_aptitude_indonesia_master_9"/>
        </record>
        <record id="survey_question_quantitative_aptitude_indonesia_master_9_col_3" model="survey.question.answer">
            <field name="value">C. 6.5%</field>
            <field name="is_correct" eval="False"/>
            <field name="answer_score">0.0</field>
            <field name="question_id" ref="survey_question_quantitative_aptitude_indonesia_master_9"/>
        </record>
        <record id="survey_question_quantitative_aptitude_indonesia_master_9_col_4" model="survey.question.answer">
            <field name="value">D. 7.5%</field>
            <field name="is_correct" eval="False"/>
            <field name="answer_score">0.0</field>
            <field name="question_id" ref="survey_question_quantitative_aptitude_indonesia_master_9"/>
        </record>

        <record id="survey_question_quantitative_aptitude_indonesia_master_10" model="survey.question">
            <field name="title">10. Dealer yang tidak jujur menggunakan berat 800 g sebagai ganti 1 kg dan menambahkan 20% pengotor dalam gula. Berapa persentase keuntungannya, jika dia mengklaim menjual barang dengan harga pokok?</field>
            <field name="question_type">simple_choice</field>
            <field name="survey_id" ref="survey_root_quantitative_aptitude_indonesia_master"/>
        </record>
        <record id="survey_question_quantitative_aptitude_indonesia_master_10_col_1" model="survey.question.answer">
            <field name="value">A. 50%</field>
            <field name="is_correct" eval="True"/>
            <field name="answer_score">3.33</field>
            <field name="question_id" ref="survey_question_quantitative_aptitude_indonesia_master_10"/>
        </record>
        <record id="survey_question_quantitative_aptitude_indonesia_master_10_col_2" model="survey.question.answer">
            <field name="value">B. 40%</field>
            <field name="is_correct" eval="False"/>
            <field name="answer_score">0.0</field>
            <field name="question_id" ref="survey_question_quantitative_aptitude_indonesia_master_10"/>
        </record>
        <record id="survey_question_quantitative_aptitude_indonesia_master_10_col_3" model="survey.question.answer">
            <field name="value">C. 25%</field>
            <field name="is_correct" eval="False"/>
            <field name="answer_score">0.0</field>
            <field name="question_id" ref="survey_question_quantitative_aptitude_indonesia_master_10"/>
        </record>
        <record id="survey_question_quantitative_aptitude_indonesia_master_10_col_4" model="survey.question.answer">
            <field name="value">D. 45.5%</field>
            <field name="is_correct" eval="False"/>
            <field name="answer_score">0.0</field>
            <field name="question_id" ref="survey_question_quantitative_aptitude_indonesia_master_10"/>
        </record>



        <record id="survey_question_quantitative_aptitude_indonesia_master_11" model="survey.question">
            <field name="title">11. Anish meminjam Rs 15.000 pada tingkat 12% dan jumlah lain pada tingkat 15% selama dua tahun. Total bunga yang dia bayar adalah Rs 9000. Berapa yang dia pinjam?</field>
            <field name="question_type">simple_choice</field>
            <field name="survey_id" ref="survey_root_quantitative_aptitude_indonesia_master"/>
        </record>
        <record id="survey_question_quantitative_aptitude_indonesia_master_11_col_1" model="survey.question.answer">
            <field name="value">A. Rs 32000</field>
            <field name="is_correct" eval="False"/>
            <field name="answer_score">0.0</field>
            <field name="question_id" ref="survey_question_quantitative_aptitude_indonesia_master_11"/>
        </record>
        <record id="survey_question_quantitative_aptitude_indonesia_master_11_col_2" model="survey.question.answer">
            <field name="value">B. Rs 33000</field>
            <field name="is_correct" eval="True"/>
            <field name="answer_score">3.33</field>
            <field name="question_id" ref="survey_question_quantitative_aptitude_indonesia_master_11"/>
        </record>
        <record id="survey_question_quantitative_aptitude_indonesia_master_11_col_3" model="survey.question.answer">
            <field name="value">C. Rs 30000</field>
            <field name="is_correct" eval="False"/>
            <field name="answer_score">0.0</field>
            <field name="question_id" ref="survey_question_quantitative_aptitude_indonesia_master_11"/>
        </record>
        <record id="survey_question_quantitative_aptitude_indonesia_master_11_col_4" model="survey.question.answer">
            <field name="value">D. Rs 63000</field>
            <field name="is_correct" eval="False"/>
            <field name="answer_score">0.0</field>
            <field name="question_id" ref="survey_question_quantitative_aptitude_indonesia_master_11"/>
        </record>



        <record id="survey_question_quantitative_aptitude_indonesia_master_12" model="survey.question">
            <field name="title">12. Jika Cl pada jumlah tertentu selama 2 tahun pada % menjadi Rs 510. Berapa SI?</field>
            <field name="question_type">simple_choice</field>
            <field name="survey_id" ref="survey_root_quantitative_aptitude_indonesia_master"/>
        </record>
        <record id="survey_question_quantitative_aptitude_indonesia_master_12_col_1" model="survey.question.answer">
            <field name="value">A. Rs 500</field>
            <field name="is_correct" eval="True"/>
            <field name="answer_score">3.33</field>
            <field name="question_id" ref="survey_question_quantitative_aptitude_indonesia_master_12"/>
        </record>
        <record id="survey_question_quantitative_aptitude_indonesia_master_12_col_2" model="survey.question.answer">
            <field name="value">B. Rs 505</field>
            <field name="is_correct" eval="False"/>
            <field name="answer_score">0.0</field>
            <field name="question_id" ref="survey_question_quantitative_aptitude_indonesia_master_12"/>
        </record>
        <record id="survey_question_quantitative_aptitude_indonesia_master_12_col_3" model="survey.question.answer">
            <field name="value">C. Rs 400</field>
            <field name="is_correct" eval="False"/>
            <field name="answer_score">0.0</field>
            <field name="question_id" ref="survey_question_quantitative_aptitude_indonesia_master_12"/>
        </record>
        <record id="survey_question_quantitative_aptitude_indonesia_master_12_col_4" model="survey.question.answer">
            <field name="value">D. Rs 475</field>
            <field name="is_correct" eval="False"/>
            <field name="answer_score">0.0</field>
            <field name="question_id" ref="survey_question_quantitative_aptitude_indonesia_master_12"/>
        </record>



        <record id="survey_question_quantitative_aptitude_indonesia_master_13" model="survey.question">
            <field name="title">13. RBI meminjamkan sejumlah tertentu kepada SBI dengan bunga sederhana selama dua tahun sebesar 20%. SBI memberikan seluruh jumlah ini kepada Bharti Telecom dengan bunga majemuk selama dua tahun pada tingkat yang sama setiap tahun. Temukan persentase pendapatan SBI pada akhir dua tahun dari seluruh jumlah.</field>
            <field name="question_type">simple_choice</field>
            <field name="survey_id" ref="survey_root_quantitative_aptitude_indonesia_master"/>
        </record>
        <record id="survey_question_quantitative_aptitude_indonesia_master_13_col_1" model="survey.question.answer">
            <field name="value">A. 4%</field>
            <field name="is_correct" eval="True"/>
            <field name="answer_score">3.33</field>
            <field name="question_id" ref="survey_question_quantitative_aptitude_indonesia_master_13"/>
        </record>
        <record id="survey_question_quantitative_aptitude_indonesia_master_13_col_2" model="survey.question.answer">
            <field name="value">B. 3(1/7)%</field>
            <field name="is_correct" eval="False"/>
            <field name="answer_score">0.0</field>
            <field name="question_id" ref="survey_question_quantitative_aptitude_indonesia_master_13"/>
        </record>
        <record id="survey_question_quantitative_aptitude_indonesia_master_13_col_3" model="survey.question.answer">
            <field name="value">C. 3(2/7)%</field>
            <field name="is_correct" eval="False"/>
            <field name="answer_score">0.0</field>
            <field name="question_id" ref="survey_question_quantitative_aptitude_indonesia_master_13"/>
        </record>
        <record id="survey_question_quantitative_aptitude_indonesia_master_13_col_4" model="survey.question.answer">
            <field name="value">D. 3(6/7)%</field>
            <field name="is_correct" eval="False"/>
            <field name="answer_score">0.0</field>
            <field name="question_id" ref="survey_question_quantitative_aptitude_indonesia_master_13"/>
        </record>



        <record id="survey_question_quantitative_aptitude_indonesia_master_14" model="survey.question">
            <field name="title">14. Seorang pria berjalan dengan kecepatan 9 km/jam. Setelah setiap km dia beristirahat selama 9 menit. Berapa waktu yang diperlukan untuk menempuh jarak 27 km?</field>
            <field name="question_type">simple_choice</field>
            <field name="survey_id" ref="survey_root_quantitative_aptitude_indonesia_master"/>
        </record>
        <record id="survey_question_quantitative_aptitude_indonesia_master_14_col_1" model="survey.question.answer">
            <field name="value">A. 6 jam</field>
            <field name="is_correct" eval="True"/>
            <field name="answer_score">3.33</field>
            <field name="question_id" ref="survey_question_quantitative_aptitude_indonesia_master_14"/>
        </record>
        <record id="survey_question_quantitative_aptitude_indonesia_master_14_col_2" model="survey.question.answer">
            <field name="value">B. 6 jam 45 menit</field>
            <field name="is_correct" eval="False"/>
            <field name="answer_score">0.0</field>
            <field name="question_id" ref="survey_question_quantitative_aptitude_indonesia_master_14"/>
        </record>
        <record id="survey_question_quantitative_aptitude_indonesia_master_14_col_3" model="survey.question.answer">
            <field name="value">C. 6 jam 54 menit</field>
            <field name="is_correct" eval="False"/>
            <field name="answer_score">0.0</field>
            <field name="question_id" ref="survey_question_quantitative_aptitude_indonesia_master_14"/>
        </record>
        <record id="survey_question_quantitative_aptitude_indonesia_master_14_col_4" model="survey.question.answer">
            <field name="value">D. 6 jam 35 menit</field>
            <field name="is_correct" eval="False"/>
            <field name="answer_score">0.0</field>
            <field name="question_id" ref="survey_question_quantitative_aptitude_indonesia_master_14"/>
        </record>



        <record id="survey_question_quantitative_aptitude_indonesia_master_15" model="survey.question">
            <field name="title">15. Dalam sebuah perjalanan, seorang pria melakukan perjalanan dengan kecepatan 64 km/jam untuk 160 km pertama, kemudian menempuh jarak 160 km berikutnya dengan kecepatan 80 km/jam. Kecepatan rata-rata dalam km per jam untuk 320 km pertama kereta api adalah?</field>
            <field name="question_type">simple_choice</field>
            <field name="survey_id" ref="survey_root_quantitative_aptitude_indonesia_master"/>
        </record>
        <record id="survey_question_quantitative_aptitude_indonesia_master_15_col_1" model="survey.question.answer">
            <field name="value">A. 35.55 km/h</field>
            <field name="is_correct" eval="False"/>
            <field name="answer_score">0.0</field>
            <field name="question_id" ref="survey_question_quantitative_aptitude_indonesia_master_15"/>
        </record>
        <record id="survey_question_quantitative_aptitude_indonesia_master_15_col_2" model="survey.question.answer">
            <field name="value">B. 71.11 km/h</field>
            <field name="is_correct" eval="True"/>
            <field name="answer_score">3.33</field>
            <field name="question_id" ref="survey_question_quantitative_aptitude_indonesia_master_15"/>
        </record>
        <record id="survey_question_quantitative_aptitude_indonesia_master_15_col_3" model="survey.question.answer">
            <field name="value">C. 36 km/h</field>
            <field name="is_correct" eval="False"/>
            <field name="answer_score">0.0</field>
            <field name="question_id" ref="survey_question_quantitative_aptitude_indonesia_master_15"/>
        </record>
        <record id="survey_question_quantitative_aptitude_indonesia_master_15_col_4" model="survey.question.answer">
            <field name="value">D. 72 km/h</field>
            <field name="is_correct" eval="False"/>
            <field name="answer_score">0.0</field>
            <field name="question_id" ref="survey_question_quantitative_aptitude_indonesia_master_15"/>
        </record>



        <record id="survey_question_quantitative_aptitude_indonesia_master_16" model="survey.question">
            <field name="title">16. Digit satuan pada hasil kali (2157)¹⁷³ adalah?</field>
            <field name="question_type">simple_choice</field>
            <field name="survey_id" ref="survey_root_quantitative_aptitude_indonesia_master"/>
        </record>
        <record id="survey_question_quantitative_aptitude_indonesia_master_16_col_1" model="survey.question.answer">
            <field name="value">A. 3</field>
            <field name="is_correct" eval="False"/>
            <field name="answer_score">0.0</field>
            <field name="question_id" ref="survey_question_quantitative_aptitude_indonesia_master_16"/>
        </record>
        <record id="survey_question_quantitative_aptitude_indonesia_master_16_col_2" model="survey.question.answer">
            <field name="value">B. 7</field>
            <field name="is_correct" eval="True"/>
            <field name="answer_score">3.33</field>
            <field name="question_id" ref="survey_question_quantitative_aptitude_indonesia_master_16"/>
        </record>
        <record id="survey_question_quantitative_aptitude_indonesia_master_16_col_3" model="survey.question.answer">
            <field name="value">C. 9</field>
            <field name="is_correct" eval="False"/>
            <field name="answer_score">0.0</field>
            <field name="question_id" ref="survey_question_quantitative_aptitude_indonesia_master_16"/>
        </record>
        <record id="survey_question_quantitative_aptitude_indonesia_master_16_col_4" model="survey.question.answer">
            <field name="value">D. 1</field>
            <field name="is_correct" eval="False"/>
            <field name="answer_score">0.0</field>
            <field name="question_id" ref="survey_question_quantitative_aptitude_indonesia_master_16"/>
        </record>



        <record id="survey_question_quantitative_aptitude_indonesia_master_17" model="survey.question">
            <field name="title">17. Manakah dari bilangan berikut yang harus ditambahkan ke 11158 agar tepat habis dibagi 77?</field>
            <field name="question_type">simple_choice</field>
            <field name="survey_id" ref="survey_root_quantitative_aptitude_indonesia_master"/>
        </record>
        <record id="survey_question_quantitative_aptitude_indonesia_master_17_col_1" model="survey.question.answer">
            <field name="value">A. 9</field>
            <field name="is_correct" eval="False"/>
            <field name="answer_score">0.0</field>
            <field name="question_id" ref="survey_question_quantitative_aptitude_indonesia_master_17"/>
        </record>
        <record id="survey_question_quantitative_aptitude_indonesia_master_17_col_2" model="survey.question.answer">
            <field name="value">B. 8</field>
            <field name="is_correct" eval="False"/>
            <field name="answer_score">0.0</field>
            <field name="question_id" ref="survey_question_quantitative_aptitude_indonesia_master_17"/>
        </record>
        <record id="survey_question_quantitative_aptitude_indonesia_master_17_col_3" model="survey.question.answer">
            <field name="value">C. 7</field>
            <field name="is_correct" eval="True"/>
            <field name="answer_score">3.33</field>
            <field name="question_id" ref="survey_question_quantitative_aptitude_indonesia_master_17"/>
        </record>
        <record id="survey_question_quantitative_aptitude_indonesia_master_17_col_4" model="survey.question.answer">
            <field name="value">D. 5</field>
            <field name="is_correct" eval="False"/>
            <field name="answer_score">0.0</field>
            <field name="question_id" ref="survey_question_quantitative_aptitude_indonesia_master_17"/>
        </record>



        <record id="survey_question_quantitative_aptitude_indonesia_master_18" model="survey.question">
            <field name="title">18. Jumlah nol dalam 18! Adalah?</field>
            <field name="question_type">simple_choice</field>
            <field name="survey_id" ref="survey_root_quantitative_aptitude_indonesia_master"/>
        </record>
        <record id="survey_question_quantitative_aptitude_indonesia_master_18_col_1" model="survey.question.answer">
            <field name="value">A. 4</field>
            <field name="is_correct" eval="False"/>
            <field name="answer_score">0.0</field>
            <field name="question_id" ref="survey_question_quantitative_aptitude_indonesia_master_18"/>
        </record>
        <record id="survey_question_quantitative_aptitude_indonesia_master_18_col_2" model="survey.question.answer">
            <field name="value">B. 6</field>
            <field name="is_correct" eval="False"/>
            <field name="answer_score">0.0</field>
            <field name="question_id" ref="survey_question_quantitative_aptitude_indonesia_master_18"/>
        </record>
        <record id="survey_question_quantitative_aptitude_indonesia_master_18_col_3" model="survey.question.answer">
            <field name="value">C. 3</field>
            <field name="is_correct" eval="True"/>
            <field name="answer_score">3.33</field>
            <field name="question_id" ref="survey_question_quantitative_aptitude_indonesia_master_18"/>
        </record>
        <record id="survey_question_quantitative_aptitude_indonesia_master_18_col_4" model="survey.question.answer">
            <field name="value">D. 8</field>
            <field name="is_correct" eval="False"/>
            <field name="answer_score">0.0</field>
            <field name="question_id" ref="survey_question_quantitative_aptitude_indonesia_master_18"/>
        </record>



        <record id="survey_question_quantitative_aptitude_indonesia_master_19" model="survey.question">
            <field name="title">19. Jika 𝑎&#179; b = abc = 180 dan a,b,c bilangan bulat positif. Maka nilai c adalah</field>
            <field name="question_type">simple_choice</field>
            <field name="survey_id" ref="survey_root_quantitative_aptitude_indonesia_master"/>
        </record>
        <record id="survey_question_quantitative_aptitude_indonesia_master_19_col_1" model="survey.question.answer">
            <field name="value">A. 110</field>
            <field name="is_correct" eval="False"/>
            <field name="answer_score">0.0</field>
            <field name="question_id" ref="survey_question_quantitative_aptitude_indonesia_master_19"/>
        </record>
        <record id="survey_question_quantitative_aptitude_indonesia_master_19_col_2" model="survey.question.answer">
            <field name="value">B. 15</field>
            <field name="is_correct" eval="False"/>
            <field name="answer_score">0.0</field>
            <field name="question_id" ref="survey_question_quantitative_aptitude_indonesia_master_19"/>
        </record>
        <record id="survey_question_quantitative_aptitude_indonesia_master_19_col_3" model="survey.question.answer">
            <field name="value">C. 25</field>
            <field name="is_correct" eval="False"/>
            <field name="answer_score">0.0</field>
            <field name="question_id" ref="survey_question_quantitative_aptitude_indonesia_master_19"/>
        </record>
        <record id="survey_question_quantitative_aptitude_indonesia_master_19_col_4" model="survey.question.answer">
            <field name="value">D. 1</field>
            <field name="is_correct" eval="True"/>
            <field name="answer_score">3.33</field>
            <field name="question_id" ref="survey_question_quantitative_aptitude_indonesia_master_19"/>
        </record>



        <record id="survey_question_quantitative_aptitude_indonesia_master_20" model="survey.question">
            <field name="title">20. Jumlah ketiga bilangan tersebut adalah 68. Jika perbandingan antara bilangan pertama dan kedua adalah 2 : 3 dan perbandingan antara kedua dan ketiga adalah 5 : 3, maka bilangan ke-2 adalah?</field>
            <field name="question_type">simple_choice</field>
            <field name="survey_id" ref="survey_root_quantitative_aptitude_indonesia_master"/>
        </record>
        <record id="survey_question_quantitative_aptitude_indonesia_master_20_col_1" model="survey.question.answer">
            <field name="value">A. 30</field>
            <field name="is_correct" eval="True"/>
            <field name="answer_score">3.33</field>
            <field name="question_id" ref="survey_question_quantitative_aptitude_indonesia_master_20"/>
        </record>
        <record id="survey_question_quantitative_aptitude_indonesia_master_20_col_2" model="survey.question.answer">
            <field name="value">B. 20</field>
            <field name="is_correct" eval="False"/>
            <field name="answer_score">0.0</field>
            <field name="question_id" ref="survey_question_quantitative_aptitude_indonesia_master_20"/>
        </record>
        <record id="survey_question_quantitative_aptitude_indonesia_master_20_col_3" model="survey.question.answer">
            <field name="value">C. 58</field>
            <field name="is_correct" eval="False"/>
            <field name="answer_score">0.0</field>
            <field name="question_id" ref="survey_question_quantitative_aptitude_indonesia_master_20"/>
        </record>
        <record id="survey_question_quantitative_aptitude_indonesia_master_20_col_4" model="survey.question.answer">
            <field name="value">D. 48</field>
            <field name="is_correct" eval="False"/>
            <field name="answer_score">0.0</field>
            <field name="question_id" ref="survey_question_quantitative_aptitude_indonesia_master_20"/>
        </record>



        <record id="survey_question_quantitative_aptitude_indonesia_master_21" model="survey.question">
            <field name="title">21. Berapa sisa jika (9&#x2076; 6 + 1) dibagi 8?</field>
            <field name="question_type">simple_choice</field>
            <field name="survey_id" ref="survey_root_quantitative_aptitude_indonesia_master"/>
        </record>
        <record id="survey_question_quantitative_aptitude_indonesia_master_21_col_1" model="survey.question.answer">
            <field name="value">A. 0</field>
            <field name="is_correct" eval="False"/>
            <field name="answer_score">0.0</field>
            <field name="question_id" ref="survey_question_quantitative_aptitude_indonesia_master_21"/>
        </record>
        <record id="survey_question_quantitative_aptitude_indonesia_master_21_col_2" model="survey.question.answer">
            <field name="value">B. 3</field>
            <field name="is_correct" eval="False"/>
            <field name="answer_score">0.0</field>
            <field name="question_id" ref="survey_question_quantitative_aptitude_indonesia_master_21"/>
        </record>
        <record id="survey_question_quantitative_aptitude_indonesia_master_21_col_3" model="survey.question.answer">
            <field name="value">C. 7</field>
            <field name="is_correct" eval="False"/>
            <field name="answer_score">0.0</field>
            <field name="question_id" ref="survey_question_quantitative_aptitude_indonesia_master_21"/>
        </record>
        <record id="survey_question_quantitative_aptitude_indonesia_master_21_col_4" model="survey.question.answer">
            <field name="value">D. 2</field>
            <field name="is_correct" eval="True"/>
            <field name="answer_score">3.33</field>
            <field name="question_id" ref="survey_question_quantitative_aptitude_indonesia_master_21"/>
        </record>



        <record id="survey_question_quantitative_aptitude_indonesia_master_22" model="survey.question">
            <field name="title">22. Perbandingan yang setara dengan 3 : 7 adalah?</field>
            <field name="question_type">simple_choice</field>
            <field name="survey_id" ref="survey_root_quantitative_aptitude_indonesia_master"/>
        </record>
        <record id="survey_question_quantitative_aptitude_indonesia_master_22_col_1" model="survey.question.answer">
            <field name="value">A. 3 : 9</field>
            <field name="is_correct" eval="False"/>
            <field name="answer_score">0.0</field>
            <field name="question_id" ref="survey_question_quantitative_aptitude_indonesia_master_22"/>
        </record>
        <record id="survey_question_quantitative_aptitude_indonesia_master_22_col_2" model="survey.question.answer">
            <field name="value">B. 6 : 10</field>
            <field name="is_correct" eval="False"/>
            <field name="answer_score">0.0</field>
            <field name="question_id" ref="survey_question_quantitative_aptitude_indonesia_master_22"/>
        </record>
        <record id="survey_question_quantitative_aptitude_indonesia_master_22_col_3" model="survey.question.answer">
            <field name="value">C. 9 : 21</field>
            <field name="is_correct" eval="True"/>
            <field name="answer_score">3.33</field>
            <field name="question_id" ref="survey_question_quantitative_aptitude_indonesia_master_22"/>
        </record>
        <record id="survey_question_quantitative_aptitude_indonesia_master_22_col_4" model="survey.question.answer">
            <field name="value">D. 18 : 49</field>
            <field name="is_correct" eval="False"/>
            <field name="answer_score">0.0</field>
            <field name="question_id" ref="survey_question_quantitative_aptitude_indonesia_master_22"/>
        </record>



        <record id="survey_question_quantitative_aptitude_indonesia_master_23" model="survey.question">
            <field name="title">23. Emas 19 kali lebih berat dari air dan tembaga 9 kali lebih berat dari air. Dalam perbandingan berapakah logam-logam ini harus dicampur sehingga campurannya mungkin 15 kali lebih berat dari air?</field>
            <field name="question_type">simple_choice</field>
            <field name="survey_id" ref="survey_root_quantitative_aptitude_indonesia_master"/>
        </record>
        <record id="survey_question_quantitative_aptitude_indonesia_master_23_col_1" model="survey.question.answer">
            <field name="value">A.2 : 5</field>
            <field name="is_correct" eval="False"/>
            <field name="answer_score">0.0</field>
            <field name="question_id" ref="survey_question_quantitative_aptitude_indonesia_master_23"/>
        </record>
        <record id="survey_question_quantitative_aptitude_indonesia_master_23_col_2" model="survey.question.answer">
            <field name="value">B. 2 : 3</field>
            <field name="is_correct" eval="False"/>
            <field name="answer_score">0.0</field>
            <field name="question_id" ref="survey_question_quantitative_aptitude_indonesia_master_23"/>
        </record>
        <record id="survey_question_quantitative_aptitude_indonesia_master_23_col_3" model="survey.question.answer">
            <field name="value">C. 3 : 1</field>
            <field name="is_correct" eval="False"/>
            <field name="answer_score">0.0</field>
            <field name="question_id" ref="survey_question_quantitative_aptitude_indonesia_master_23"/>
        </record>
        <record id="survey_question_quantitative_aptitude_indonesia_master_23_col_4" model="survey.question.answer">
            <field name="value">D. 3 : 2</field>
            <field name="is_correct" eval="True"/>
            <field name="answer_score">3.33</field>
            <field name="question_id" ref="survey_question_quantitative_aptitude_indonesia_master_23"/>
        </record>



        <record id="survey_question_quantitative_aptitude_indonesia_master_24" model="survey.question">
            <field name="title">24. A dua tahun lebih tua dari B yang dua kali lebih tua dari C. Jika jumlah usia A, B, dan C adalah 27, berapa umur B?</field>
            <field name="question_type">simple_choice</field>
            <field name="survey_id" ref="survey_root_quantitative_aptitude_indonesia_master"/>
        </record>
        <record id="survey_question_quantitative_aptitude_indonesia_master_24_col_1" model="survey.question.answer">
            <field name="value">A. 8</field>
            <field name="is_correct" eval="False"/>
            <field name="answer_score">0.0</field>
            <field name="question_id" ref="survey_question_quantitative_aptitude_indonesia_master_24"/>
        </record>
        <record id="survey_question_quantitative_aptitude_indonesia_master_24_col_2" model="survey.question.answer">
            <field name="value">B. 9</field>
            <field name="is_correct" eval="False"/>
            <field name="answer_score">0.0</field>
            <field name="question_id" ref="survey_question_quantitative_aptitude_indonesia_master_24"/>
        </record>
        <record id="survey_question_quantitative_aptitude_indonesia_master_24_col_3" model="survey.question.answer">
            <field name="value">C. 10</field>
            <field name="is_correct" eval="True"/>
            <field name="answer_score">3.33</field>
            <field name="question_id" ref="survey_question_quantitative_aptitude_indonesia_master_24"/>
        </record>
        <record id="survey_question_quantitative_aptitude_indonesia_master_24_col_4" model="survey.question.answer">
            <field name="value">D. 12</field>
            <field name="is_correct" eval="False"/>
            <field name="answer_score">0.0</field>
            <field name="question_id" ref="survey_question_quantitative_aptitude_indonesia_master_24"/>
        </record>



        <record id="survey_question_quantitative_aptitude_indonesia_master_25" model="survey.question">
            <field name="title">25. Sachin lebih muda dari Rahun 7 tahun. Jika usia mereka dalam perbandingan masing-masing 7 : 9, berapa umur Sachin?</field>
            <field name="question_type">simple_choice</field>
            <field name="survey_id" ref="survey_root_quantitative_aptitude_indonesia_master"/>
        </record>
        <record id="survey_question_quantitative_aptitude_indonesia_master_25_col_1" model="survey.question.answer">
            <field name="value">A. 12 tahun</field>
            <field name="is_correct" eval="False"/>
            <field name="answer_score">0.0</field>
            <field name="question_id" ref="survey_question_quantitative_aptitude_indonesia_master_25"/>
        </record>
        <record id="survey_question_quantitative_aptitude_indonesia_master_25_col_2" model="survey.question.answer">
            <field name="value">B. 16 tahun</field>
            <field name="is_correct" eval="False"/>
            <field name="answer_score">0.0</field>
            <field name="question_id" ref="survey_question_quantitative_aptitude_indonesia_master_25"/>
        </record>
        <record id="survey_question_quantitative_aptitude_indonesia_master_25_col_3" model="survey.question.answer">
            <field name="value">C. 20 tahun</field>
            <field name="is_correct" eval="False"/>
            <field name="answer_score">0.0</field>
            <field name="question_id" ref="survey_question_quantitative_aptitude_indonesia_master_25"/>
        </record>
        <record id="survey_question_quantitative_aptitude_indonesia_master_25_col_4" model="survey.question.answer">
            <field name="value">D. 24.5 tahun</field>
            <field name="is_correct" eval="True"/>
            <field name="answer_score">3.33</field>
            <field name="question_id" ref="survey_question_quantitative_aptitude_indonesia_master_25"/>
        </record>



        <record id="survey_question_quantitative_aptitude_indonesia_master_26" model="survey.question">
            <field name="title">26. Temukan istilah yang hilang dari ekspresi yang diberikan:</field>
            <field name="question_type">simple_choice</field>
            <field name="survey_id" ref="survey_root_quantitative_aptitude_indonesia_master"/>
            <field name="description" type="html">
                <div class="shadow bg-white rounded">
                    <blockquote style="border-left: 10px solid;border-color: #3399ff;">
                        <p style="margin-bottom:0;">
                            18.834 + 818.34 - ? = 618.43
                        </p>
                    </blockquote>
                </div>
            </field>
        </record>
        <record id="survey_question_quantitative_aptitude_indonesia_master_26_col_1" model="survey.question.answer">
            <field name="value">A.217.644</field>
            <field name="is_correct" eval="False"/>
            <field name="answer_score">0.0</field>
            <field name="question_id" ref="survey_question_quantitative_aptitude_indonesia_master_26"/>
        </record>
        <record id="survey_question_quantitative_aptitude_indonesia_master_26_col_2" model="survey.question.answer">
            <field name="value">B. 218.744</field>
            <field name="is_correct" eval="True"/>
            <field name="answer_score">3.33</field>
            <field name="question_id" ref="survey_question_quantitative_aptitude_indonesia_master_26"/>
        </record>
        <record id="survey_question_quantitative_aptitude_indonesia_master_26_col_3" model="survey.question.answer">
            <field name="value">C. 217.74</field>
            <field name="is_correct" eval="False"/>
            <field name="answer_score">0.0</field>
            <field name="question_id" ref="survey_question_quantitative_aptitude_indonesia_master_26"/>
        </record>
        <record id="survey_question_quantitative_aptitude_indonesia_master_26_col_4" model="survey.question.answer">
            <field name="value">D. 217.844</field>
            <field name="is_correct" eval="False"/>
            <field name="answer_score">0.0</field>
            <field name="question_id" ref="survey_question_quantitative_aptitude_indonesia_master_26"/>
        </record>



        <record id="survey_question_quantitative_aptitude_indonesia_master_27" model="survey.question">
            <field name="title">27. Nilai dari:</field>
            <field name="question_type">simple_choice</field>
            <field name="survey_id" ref="survey_root_quantitative_aptitude_indonesia_master"/>
            <field name="description" type="html">
                <p>
                    <img class="img-fluid o_we_custom_image d-block" src="/equip3_hr_survey_extend/static/img/question_quantitative_27.png" style="width: 10%;"/>
                    <br/>
                </p>
            </field>
        </record>
        <record id="survey_question_quantitative_aptitude_indonesia_master_27_col_1" model="survey.question.answer">
            <field name="value">A. 98</field>
            <field name="is_correct" eval="False"/>
            <field name="answer_score">0.0</field>
            <field name="question_id" ref="survey_question_quantitative_aptitude_indonesia_master_27"/>
        </record>
        <record id="survey_question_quantitative_aptitude_indonesia_master_27_col_2" model="survey.question.answer">
            <field name="value">B. 35</field>
            <field name="is_correct" eval="False"/>
            <field name="answer_score">0.0</field>
            <field name="question_id" ref="survey_question_quantitative_aptitude_indonesia_master_27"/>
        </record>
        <record id="survey_question_quantitative_aptitude_indonesia_master_27_col_3" model="survey.question.answer">
            <field name="value">C. 350</field>
            <field name="is_correct" eval="False"/>
            <field name="answer_score">0.0</field>
            <field name="question_id" ref="survey_question_quantitative_aptitude_indonesia_master_27"/>
        </record>
        <record id="survey_question_quantitative_aptitude_indonesia_master_27_col_4" model="survey.question.answer">
            <field name="value">D. Tidak satupun diatas</field>
            <field name="is_correct" eval="True"/>
            <field name="answer_score">3.33</field>
            <field name="question_id" ref="survey_question_quantitative_aptitude_indonesia_master_27"/>
        </record>



        <record id="survey_question_quantitative_aptitude_indonesia_master_28" model="survey.question">
            <field name="title">28. </field>
            <field name="question_type">simple_choice</field>
            <field name="survey_id" ref="survey_root_quantitative_aptitude_indonesia_master"/>
            <field name="description" type="html">
                <p>
                    <img class="img-fluid o_we_custom_image d-block" src="/equip3_hr_survey_extend/static/img/question_quantitative_28.jpeg" style="width: 20%;"/>
                    <br/>
                    <h3> Adalah sama dengan</h3>
                </p>
            </field>
        </record>
        <record id="survey_question_quantitative_aptitude_indonesia_master_28_col_1" model="survey.question.answer">
            <field name="value">A. 3</field>
            <field name="is_correct" eval="False"/>
            <field name="answer_score">0.0</field>
            <field name="question_id" ref="survey_question_quantitative_aptitude_indonesia_master_28"/>
        </record>
        <record id="survey_question_quantitative_aptitude_indonesia_master_28_col_2" model="survey.question.answer">
            <field name="value">B. 4</field>
            <field name="is_correct" eval="False"/>
            <field name="answer_score">0.0</field>
            <field name="question_id" ref="survey_question_quantitative_aptitude_indonesia_master_28"/>
        </record>
        <record id="survey_question_quantitative_aptitude_indonesia_master_28_col_3" model="survey.question.answer">
            <field name="value">C. 5</field>
            <field name="is_correct" eval="False"/>
            <field name="answer_score">0.0</field>
            <field name="question_id" ref="survey_question_quantitative_aptitude_indonesia_master_28"/>
        </record>
        <record id="survey_question_quantitative_aptitude_indonesia_master_28_col_4" model="survey.question.answer">
            <field name="value">D. Tidak satupun diatas</field>
            <field name="is_correct" eval="True"/>
            <field name="answer_score">3.33</field>
            <field name="question_id" ref="survey_question_quantitative_aptitude_indonesia_master_28"/>
        </record>



        <record id="survey_question_quantitative_aptitude_indonesia_master_29" model="survey.question">
            <field name="title">29. Pekerja A menyelesaikan tugas dalam 8 hari dan pekerja B menyelesaikan tugas yang sama dalam 10 hari. Jika A dan B bekerja bersama-sama, dalam berapa hari mereka akan menyelesaikan tugas tersebut?</field>
            <field name="question_type">simple_choice</field>
            <field name="survey_id" ref="survey_root_quantitative_aptitude_indonesia_master"/>
        </record>
        <record id="survey_question_quantitative_aptitude_indonesia_master_29_col_1" model="survey.question.answer">
            <field name="value">A. 40/10 hari</field>
            <field name="is_correct" eval="False"/>
            <field name="answer_score">0.0</field>
            <field name="question_id" ref="survey_question_quantitative_aptitude_indonesia_master_29"/>
        </record>
        <record id="survey_question_quantitative_aptitude_indonesia_master_29_col_2" model="survey.question.answer">
            <field name="value">B. 40/9 hari</field>
            <field name="is_correct" eval="True"/>
            <field name="answer_score">3.33</field>
            <field name="question_id" ref="survey_question_quantitative_aptitude_indonesia_master_29"/>
        </record>
        <record id="survey_question_quantitative_aptitude_indonesia_master_29_col_3" model="survey.question.answer">
            <field name="value">C. 40/8 hari</field>
            <field name="is_correct" eval="False"/>
            <field name="answer_score">0.0</field>
            <field name="question_id" ref="survey_question_quantitative_aptitude_indonesia_master_29"/>
        </record>
        <record id="survey_question_quantitative_aptitude_indonesia_master_29_col_4" model="survey.question.answer">
            <field name="value">D. 40/7 hari</field>
            <field name="is_correct" eval="False"/>
            <field name="answer_score">0.0</field>
            <field name="question_id" ref="survey_question_quantitative_aptitude_indonesia_master_29"/>
        </record>



        <record id="survey_question_quantitative_aptitude_indonesia_master_30" model="survey.question">
            <field name="title">30. Nilai dari 5&#188; x (125)&#8304;&#183;&#178;&#8309;</field>
            <field name="question_type">simple_choice</field>
            <field name="survey_id" ref="survey_root_quantitative_aptitude_indonesia_master"/>
        </record>
        <record id="survey_question_quantitative_aptitude_indonesia_master_30_col_1" model="survey.question.answer">
            <field name="value">A.  &#8730;5</field>
            <field name="is_correct" eval="False"/>
            <field name="answer_score">0.0</field>
            <field name="question_id" ref="survey_question_quantitative_aptitude_indonesia_master_30"/>
        </record>
        <record id="survey_question_quantitative_aptitude_indonesia_master_30_col_2" model="survey.question.answer">
            <field name="value">B. 5 &#8730;5</field>
            <field name="is_correct" eval="False"/>
            <field name="answer_score">0.0</field>
            <field name="question_id" ref="survey_question_quantitative_aptitude_indonesia_master_30"/>
        </record>
        <record id="survey_question_quantitative_aptitude_indonesia_master_30_col_3" model="survey.question.answer">
            <field name="value">C. 5</field>
            <field name="is_correct" eval="True"/>
            <field name="answer_score">3.43</field>
            <field name="question_id" ref="survey_question_quantitative_aptitude_indonesia_master_30"/>
        </record>
        <record id="survey_question_quantitative_aptitude_indonesia_master_30_col_4" model="survey.question.answer">
            <field name="value">D. 25</field>
            <field name="is_correct" eval="False"/>
            <field name="answer_score">0.0</field>
            <field name="question_id" ref="survey_question_quantitative_aptitude_indonesia_master_30"/>
        </record>


    </data>
</odoo>